userLoginTool/__init__.py
userLoginTool/app.py
userLoginTool/utils/__init__.py
userLoginTool/utils/constants.py
userLoginTool/utils/db_helper.py
userLoginTool/utils/self_defined_errors.py
utils/__init__.py
utils/constants.py
utils/db_helper.py
utils/self_defined_errors.py
login_and_logout_tool-0.0.2.dist-info/LICENSE
login_and_logout_tool-0.0.2.dist-info/METADATA
login_and_logout_tool-0.0.2.dist-info/WHEEL
login_and_logout_tool-0.0.2.dist-info/top_level.txt
login_and_logout_tool-0.0.2.dist-info/RECORD
