Metadata-Version: 2.1
Name: login-and-logout-tool
Version: 0.0.2
Summary: a tool for dealing with login and logout
Home-page: https://github.com/Martin-Jia/logInNOut
Author: Mingda Jia
Author-email: martinchia93@outlook.com
License: UNKNOWN
Platform: UNKNOWN
License-File: LICENSE
Requires-Dist: pyjwt
Requires-Dist: pymongo
